phasors/__init__.py
phasors/phasor.py
phasors-0.0.1.dist-info/LICENSE
phasors-0.0.1.dist-info/WHEEL
phasors-0.0.1.dist-info/METADATA
phasors-0.0.1.dist-info/RECORD
