Metadata-Version: 2.1
Name: phasors
Version: 0.0.1
Summary: Phasor - A means to measure complex values with magnitude and angle.
Author-email: Joe Stanley <engineerjoe440@yahoo.com>
Maintainer-email: Joe Stanley <engineerjoe440@yahoo.com>
Classifier: Programming Language :: Python :: 3
Classifier: License :: OSI Approved :: MIT License
Classifier: Operating System :: OS Independent
Requires-Dist: numpy
Requires-Dist: pytest >=2.7.3 ; extra == "test"
Project-URL: Documentation, https://phasors.readthedocs.io/en/latest/
Project-URL: Home, https://github.com/engineerjoe440/phasors
Project-URL: Issues, https://github.com/engineerjoe440/phasors/issues
Project-URL: Repository, https://github.com/engineerjoe440/phasors
Provides-Extra: test
